{"tfjsVersion":"1.3.1","tmVersion":"2.4.5","packageVersion":"0.8.4-alpha2","packageName":"@teachablemachine/image","timeStamp":"2022-10-28T05:13:15.186Z","userMetadata":{},"modelName":"tm-my-image-model","labels":["카마도 탄지로","카마도 네즈코","아가츠마 젠이츠","하시바라 이노스케","렌고쿠 쿄쥬로","우즈이 텐겐","칸로지 미츠리","히메지마 교메이","토키토 무이치로","이구로 오바나이","토미오카 기유","코쵸우 시노부","시나즈가와 사네미","코쵸우 카나에","우로코다키 사콘지","쿠와지마 지고로","츠유리 카나오","시나즈가와 겐야","칸자키 아오이","카이가쿠","무라타","우부야시키 카가야","하가네즈카 호타루","키부츠지 무잔","스사마루","야하바","루이","코쿠시보","아카자","도우마","굣코","다키","한텐구","나키메","쿄우가이","엔무","타마요","유시로","규타로"],"imageSize":224}